README.md
setup.cfg
setup.py
src/__init__.py
src/auth.py
src/handlers.py
src/utils.py
udiscord/__init__.py
udiscord/client.py
udiscord.egg-info/PKG-INFO
udiscord.egg-info/SOURCES.txt
udiscord.egg-info/dependency_links.txt
udiscord.egg-info/requires.txt
udiscord.egg-info/top_level.txt
udiscord/_async/__init__.py
udiscord/_async/client.py
udiscord/_async/ws/__init__.py
udiscord/_async/ws/socket.py
udiscord/_async/ws/socket_handler.py
udiscord/utils/__init__.py
udiscord/utils/exceptions.py
udiscord/utils/logger.py
udiscord/utils/requester.py
udiscord/utils/objects/__init__.py
udiscord/utils/objects/audit.py
udiscord/utils/objects/channel.py
udiscord/utils/objects/guild.py
udiscord/utils/objects/invites.py
udiscord/utils/objects/location_metadata.py
udiscord/utils/objects/message.py
udiscord/utils/objects/objects.py
udiscord/utils/objects/user.py
udiscord/utils/objects/args/__init__.py
udiscord/utils/objects/args/audit_action.py
udiscord/utils/objects/args/chnnel_types.py
udiscord/utils/objects/args/event_types.py
udiscord/utils/objects/event/__init__.py
udiscord/utils/objects/event/account_info.py
udiscord/utils/objects/event/event.py
udiscord/utils/objects/event/event_types.py
udiscord/ws/__init__.py
udiscord/ws/socket.py
udiscord/ws/socket_handler.py