Metadata-Version: 2.4
Name: udiscord
Version: 1.4
Summary: Library for creating discord bots and scripts.
Home-page: https://github.com/alx0rr/discord
Download-URL: https://github.com/alx0rr/discord/archive/refs/heads/main.zip
Author: alx0rr
Author-email: anon.mail.al@proton.me
License: MIT
Keywords: discord.py,discord,discord-py,discord-bot,api,python,python3,python3.x,alx0rr,official,sync,async,udiscord,discord-self-bot
Requires-Dist: requests
Requires-Dist: ujson
Requires-Dist: logging
Requires-Dist: websocket-client
Requires-Dist: colorama
Requires-Dist: aiohttp
Dynamic: author
Dynamic: author-email
Dynamic: description
Dynamic: description-content-type
Dynamic: download-url
Dynamic: home-page
Dynamic: keywords
Dynamic: license
Dynamic: requires-dist
Dynamic: summary
